remove_emojis_package/__init__.py
remove_emojis_package/remove_emojis.py
sebatools/__init__.py
sebatools/check_duplicates.py
sebatools/remove_emojis.py
sebatools/row_iterator.py
sebatools-0.6.4.dist-info/METADATA
sebatools-0.6.4.dist-info/WHEEL
sebatools-0.6.4.dist-info/top_level.txt
sebatools-0.6.4.dist-info/RECORD
