Metadata-Version: 2.1
Name: sebatools
Version: 0.6.4
Summary: A package to remove emojis from text and more...
Author: Sebastiaan Hendriks
Author-email: sgtahendriks@gmail.com
Requires-Python: >=3.9
